youqu/CURRENT
youqu/README.md
youqu/conftest.py
youqu/env.sh
youqu/manage.py
youqu/pytest.ini
youqu/ruff.toml
youqu/startproject.py
youqu/test.py
youqu/apps/__init__.py
youqu/setting/__init__.py
youqu/setting/globalconfig.ini
youqu/setting/globalconfig.py
youqu/setting/pmsmark.ini
youqu/setting/pylintrc.cfg
youqu/setting/skipif.py
youqu/setting/sleepx.ini
youqu/setting/template/ci.json
youqu/setting/template/language.ini
youqu/setting/template/app_template/${app_name}_assert.py-tpl
youqu/setting/template/app_template/.gitignore-tpl
youqu/setting/template/app_template/__init__.py-tpl
youqu/setting/template/app_template/config.ini-tpl
youqu/setting/template/app_template/config.py-tpl
youqu/setting/template/app_template/conftest.py-tpl
youqu/setting/template/app_template/control-tpl
youqu/setting/template/app_template/mycase.csv-tpl
youqu/setting/template/app_template/case/__init__.py-tpl
youqu/setting/template/app_template/case/base_case.py-tpl
youqu/setting/template/app_template/case/test_mycase_001.py-tpl
youqu/setting/template/app_template/case/test_mycase_002.py-tpl
youqu/setting/template/app_template/case/assert_res/readme
youqu/setting/template/app_template/widget/${app_name}_widget.py-tpl
youqu/setting/template/app_template/widget/__init__.py-tpl
youqu/setting/template/app_template/widget/base_widget.py-tpl
youqu/setting/template/app_template/widget/other.ini-tpl
youqu/setting/template/app_template/widget/other_widget.py-tpl
youqu/setting/template/app_template/widget/ui.ini-tpl
youqu/setting/template/app_template/widget/case_res/readme
youqu/setting/template/app_template/widget/pic_res/readme
youqu/src/__init__.py
youqu/src/assert_common.py
youqu/src/button_center.py
youqu/src/calculate.py
youqu/src/cmdctl.py
youqu/src/csvctl.py
youqu/src/custom_exception.py
youqu/src/dbus_utils.py
youqu/src/desktop.py
youqu/src/dogtail_utils.py
youqu/src/filectl.py
youqu/src/filter_image.py
youqu/src/image_utils.py
youqu/src/mouse_key.py
youqu/src/ocr_utils.py
youqu_framework-2.14.4.dist-info/METADATA
youqu_framework-2.14.4.dist-info/WHEEL
youqu_framework-2.14.4.dist-info/entry_points.txt
youqu_framework-2.14.4.dist-info/RECORD
