Metadata-Version: 2.1
Name: youqu-framework
Version: 2.14.4
Summary: youqu
Project-URL: Source, https://github.com/linuxdeepin/youqu
Project-URL: Documentation, https://github.com/linuxdeepin/youqu
Author-email: wangpeng <781757836@qq.com>
Classifier: License :: OSI Approved :: GNU General Public License v2 (GPLv2)
Classifier: Operating System :: OS Independent
Classifier: Programming Language :: Python :: 3.6
Requires-Python: >=3.6
